README.rst
setup.py
f5_heat/__init__.py
f5_heat/resources/__init__.py
f5_heat/resources/f5_bigip_device.py
f5_heat/resources/f5_cm_cluster.py
f5_heat/resources/f5_cm_sync.py
f5_heat/resources/f5_ltm_pool.py
f5_heat/resources/f5_ltm_virtualserver.py
f5_heat/resources/f5_sys_iappcompositetemplate.py
f5_heat/resources/f5_sys_iappfulltemplate.py
f5_heat/resources/f5_sys_iappservice.py
f5_heat/resources/f5_sys_partition.py
f5_heat/resources/f5_sys_save.py
f5_heat/resources/common/__init__.py
f5_heat/resources/common/mixins.py
f5_openstack_heat_plugins.egg-info/PKG-INFO
f5_openstack_heat_plugins.egg-info/SOURCES.txt
f5_openstack_heat_plugins.egg-info/dependency_links.txt
f5_openstack_heat_plugins.egg-info/requires.txt
f5_openstack_heat_plugins.egg-info/top_level.txt