Metadata-Version: 1.1
Name: f5-openstack-heat-plugins
Version: 10.0.0
Summary: F5 Networks OpenStack Heat Plugin Library
Home-page: https://github.com/F5Networks/f5-openstack-heat-plugins/
Author: F5 Networks
Author-email: f5_openstack_heat@f5.com
License: Apache License, Version 2.0
Keywords: F5,openstack,heat,bigip,orchestration
Platform: UNKNOWN
Classifier: Development Status :: 5 - Production/Stable
Classifier: License :: OSI Approved :: Apache Software License
Classifier: Operating System :: OS Independent
Classifier: Programming Language :: Python
Classifier: Intended Audience :: System Administrators
